ghostport/__init__.py
ghostport/ghostport.py
ghostport-0.0.4.dist-info/METADATA
ghostport-0.0.4.dist-info/WHEEL
ghostport-0.0.4.dist-info/top_level.txt
ghostport-0.0.4.dist-info/RECORD
