Metadata-Version: 2.1
Name: ghostport
Version: 0.0.4
Summary: GhostPort Python SDK
Home-page: https://github.com/ghostport/python-sdk
Author: GhostPort
Author-email: admin@ghostport.io
License: MIT
Keywords: feature,flag,ghostport
Platform: UNKNOWN
Classifier: License :: OSI Approved :: MIT License
Classifier: Programming Language :: Python :: 3
Classifier: Programming Language :: Python :: 3.0
Classifier: Programming Language :: Python :: 3.1
Classifier: Programming Language :: Python :: 3.2
Classifier: Programming Language :: Python :: 3.3
Classifier: Programming Language :: Python :: 3.4
Classifier: Programming Language :: Python :: 3.5
Classifier: Programming Language :: Python :: 3.6
Classifier: Programming Language :: Python :: 3.7
Classifier: Programming Language :: Python :: 3.8
Requires-Dist: requests (>=2.24.0)
